{
  "prompt_version": "v4",
  "collected_at": "2025-12-10T13:15:54.751033",
  "entry_count": 23,
  "entries": [
    {
      "timestamp": "2025-12-10T13:15:54.750952",
      "entity_type": "email",
      "entity_value": "chabba4444@gmail.com",
      "predicted_fraud": true,
      "actual_fraud": false,
      "risk_score": 0.75,
      "confidence": 0.85,
      "reasoning": "The entity exhibits multiple high-risk behavioral patterns, including the use of 10 unique devices and 44 unique IP addresses for a single email, which significantly elevates the risk score. Additiona",
      "error_type": "false_positive",
      "prompt_version": "v4"
    },
    {
      "timestamp": "2025-12-10T13:15:54.750967",
      "entity_type": "email",
      "entity_value": "aoehringlopez@gmail.com",
      "predicted_fraud": true,
      "actual_fraud": false,
      "risk_score": 0.65,
      "confidence": 0.75,
      "reasoning": "The entity exhibits high-risk behavioral patterns, particularly with a very high number of unique IPs (236) for a single email, which is significantly above the threshold of 5. Additionally, the stand",
      "error_type": "false_positive",
      "prompt_version": "v4"
    },
    {
      "timestamp": "2025-12-10T13:15:54.750970",
      "entity_type": "email",
      "entity_value": "shavit.c.2008@gmail.com",
      "predicted_fraud": true,
      "actual_fraud": false,
      "risk_score": 0.65,
      "confidence": 0.75,
      "reasoning": "The entity shows multiple high-risk behavioral patterns, including the use of 6 unique devices and 18 unique IP addresses for a single email, which indicates suspicious behavior. Additionally, the sta",
      "error_type": "false_positive",
      "prompt_version": "v4"
    },
    {
      "timestamp": "2025-12-10T13:15:54.750973",
      "entity_type": "email",
      "entity_value": "cfergus41@yahoo.com",
      "predicted_fraud": true,
      "actual_fraud": false,
      "risk_score": 0.55,
      "confidence": 0.7,
      "reasoning": "The entity shows suspicious behavior with a high number of unique IPs (22) for only 2 devices, indicating potential account takeover or fraudulent activity. The high standard deviation in transaction ",
      "error_type": "false_positive",
      "prompt_version": "v4"
    },
    {
      "timestamp": "2025-12-10T13:15:54.750975",
      "entity_type": "email",
      "entity_value": "miamulah@outlook.com",
      "predicted_fraud": true,
      "actual_fraud": false,
      "risk_score": 0.55,
      "confidence": 0.7,
      "reasoning": "The entity exhibits suspicious behavior with a high number of unique IPs (32) for only 2 devices, indicating potential account sharing or misuse. Additionally, the high standard deviation in transacti",
      "error_type": "false_positive",
      "prompt_version": "v4"
    },
    {
      "timestamp": "2025-12-10T13:15:54.750977",
      "entity_type": "email",
      "entity_value": "henriqueenzoperera@gmail.com",
      "predicted_fraud": true,
      "actual_fraud": false,
      "risk_score": 0.55,
      "confidence": 0.7,
      "reasoning": "The entity shows suspicious behavior with 7 unique IPs for a single email, which is a significant red flag. Although there is only one device, the high number of IPs indicates potential attempts to ma",
      "error_type": "false_positive",
      "prompt_version": "v4"
    },
    {
      "timestamp": "2025-12-10T13:15:54.750978",
      "entity_type": "email",
      "entity_value": "mmoonga063@gmail.com",
      "predicted_fraud": true,
      "actual_fraud": false,
      "risk_score": 0.55,
      "confidence": 0.7,
      "reasoning": "The entity exhibits suspicious behavior with a high number of unique IPs (56) for only 2 devices, which indicates potential fraud risk. The average transaction value is relatively high at $427.125, an",
      "error_type": "false_positive",
      "prompt_version": "v4"
    },
    {
      "timestamp": "2025-12-10T13:15:54.750980",
      "entity_type": "email",
      "entity_value": "lucassiejr@gmail.com",
      "predicted_fraud": true,
      "actual_fraud": false,
      "risk_score": 0.65,
      "confidence": 0.75,
      "reasoning": "The entity shows multiple devices (4) and a very high number of unique IPs (41) for a single email, which indicates suspicious behavior. Additionally, the standard deviation of transaction values is r",
      "error_type": "false_positive",
      "prompt_version": "v4"
    },
    {
      "timestamp": "2025-12-10T13:15:54.750982",
      "entity_type": "email",
      "entity_value": "rrmmr7471@gmail.com",
      "predicted_fraud": true,
      "actual_fraud": false,
      "risk_score": 0.55,
      "confidence": 0.7,
      "reasoning": "The entity exhibits suspicious behavior with 3 unique devices and 7 unique IPs, which indicates potential risk. The average transaction value is moderate, but the standard deviation is relatively high",
      "error_type": "false_positive",
      "prompt_version": "v4"
    },
    {
      "timestamp": "2025-12-10T13:15:54.750983",
      "entity_type": "email",
      "entity_value": "tominationarmy@gmail.com",
      "predicted_fraud": true,
      "actual_fraud": false,
      "risk_score": 0.55,
      "confidence": 0.7,
      "reasoning": "The entity shows suspicious behavior with 3 unique devices and 7 unique IPs, which indicates potential fraud risk. The transaction value variance is moderate, but the overall transaction volume is low",
      "error_type": "false_positive",
      "prompt_version": "v4"
    },
    {
      "timestamp": "2025-12-10T13:15:54.750985",
      "entity_type": "email",
      "entity_value": "jessica.bellamy@trilliumnc.org",
      "predicted_fraud": true,
      "actual_fraud": false,
      "risk_score": 0.55,
      "confidence": 0.7,
      "reasoning": "The entity exhibits suspicious behavior with 3 unique devices and 8 unique IPs, which indicates potential risk. While the average transaction value is relatively low, the presence of multiple IPs sugg",
      "error_type": "false_positive",
      "prompt_version": "v4"
    },
    {
      "timestamp": "2025-12-10T13:15:54.750987",
      "entity_type": "email",
      "entity_value": "antonylp648@gmail.com",
      "predicted_fraud": true,
      "actual_fraud": false,
      "risk_score": 0.65,
      "confidence": 0.75,
      "reasoning": "The entity shows multiple devices (5) and IPs (7) associated with a single email, which indicates suspicious behavior. Additionally, the standard deviation of transaction values is high, suggesting va",
      "error_type": "false_positive",
      "prompt_version": "v4"
    },
    {
      "timestamp": "2025-12-10T13:15:54.750988",
      "entity_type": "email",
      "entity_value": "rudyrios1017@gmail.com",
      "predicted_fraud": true,
      "actual_fraud": false,
      "risk_score": 0.65,
      "confidence": 0.75,
      "reasoning": "The entity exhibits multiple high-risk behavioral patterns, including the use of 10 unique devices and 6 unique IP addresses for a single email, which indicates suspicious behavior. The average transa",
      "error_type": "false_positive",
      "prompt_version": "v4"
    },
    {
      "timestamp": "2025-12-10T13:15:54.750990",
      "entity_type": "email",
      "entity_value": "reinier@ahomewithin.org",
      "predicted_fraud": true,
      "actual_fraud": false,
      "risk_score": 0.65,
      "confidence": 0.75,
      "reasoning": "The entity exhibits multiple high-risk behavioral patterns, including the use of 13 unique devices and 7 unique IPs for a single email, which indicates suspicious behavior. Additionally, the standard ",
      "error_type": "false_positive",
      "prompt_version": "v4"
    },
    {
      "timestamp": "2025-12-10T13:15:54.750992",
      "entity_type": "email",
      "entity_value": "sandrine.magnon@free.fr",
      "predicted_fraud": true,
      "actual_fraud": false,
      "risk_score": 0.55,
      "confidence": 0.7,
      "reasoning": "The entity shows suspicious behavior with 7 unique IP addresses for a single email, which indicates potential fraud risk. Additionally, the standard deviation of transaction values is relatively high,",
      "error_type": "false_positive",
      "prompt_version": "v4"
    },
    {
      "timestamp": "2025-12-10T13:15:54.750993",
      "entity_type": "email",
      "entity_value": "erikmanzinis@gmail.com",
      "predicted_fraud": true,
      "actual_fraud": false,
      "risk_score": 0.55,
      "confidence": 0.7,
      "reasoning": "The entity shows suspicious behavior with a high number of unique IPs (12) while using a single device, which indicates potential fraud risk. Additionally, the standard deviation of transaction values",
      "error_type": "false_positive",
      "prompt_version": "v4"
    },
    {
      "timestamp": "2025-12-10T13:15:54.750995",
      "entity_type": "email",
      "entity_value": "jrizik35@gmail.com",
      "predicted_fraud": true,
      "actual_fraud": false,
      "risk_score": 0.55,
      "confidence": 0.7,
      "reasoning": "The entity exhibits suspicious behavior with 2 unique devices and 7 unique IPs, which indicates potential risk. The standard deviation of transaction values is relatively high, suggesting variability ",
      "error_type": "false_positive",
      "prompt_version": "v4"
    },
    {
      "timestamp": "2025-12-10T13:15:54.750996",
      "entity_type": "email",
      "entity_value": "kevin@cybertronixllc.com",
      "predicted_fraud": true,
      "actual_fraud": false,
      "risk_score": 0.55,
      "confidence": 0.7,
      "reasoning": "The entity exhibits suspicious behavior with a high number of unique IPs (39) for only 2 devices, which indicates potential account takeover or fraudulent activity. The standard deviation of transacti",
      "error_type": "false_positive",
      "prompt_version": "v4"
    },
    {
      "timestamp": "2025-12-10T13:15:54.750998",
      "entity_type": "email",
      "entity_value": "chrisidl69@gmail.com",
      "predicted_fraud": true,
      "actual_fraud": false,
      "risk_score": 0.55,
      "confidence": 0.7,
      "reasoning": "The entity exhibits suspicious behavior with a high number of unique IPs (25) while using a single device, which indicates potential fraud risk. The standard deviation of transaction values is also re",
      "error_type": "false_positive",
      "prompt_version": "v4"
    },
    {
      "timestamp": "2025-12-10T13:15:54.751000",
      "entity_type": "email",
      "entity_value": "diti1992@icloud.com",
      "predicted_fraud": true,
      "actual_fraud": false,
      "risk_score": 0.55,
      "confidence": 0.7,
      "reasoning": "The entity exhibits multiple devices and IPs associated with a single email, which raises suspicion. Although the average transaction value is moderate, the presence of 4 unique devices and 8 unique I",
      "error_type": "false_positive",
      "prompt_version": "v4"
    },
    {
      "timestamp": "2025-12-10T13:15:54.751001",
      "entity_type": "email",
      "entity_value": "mgscoggins@gmail.com",
      "predicted_fraud": true,
      "actual_fraud": false,
      "risk_score": 0.55,
      "confidence": 0.7,
      "reasoning": "The entity exhibits suspicious behavior with 3 unique devices and 13 unique IP addresses, which indicates potential account sharing or misuse. The transaction value standard deviation is relatively hi",
      "error_type": "false_positive",
      "prompt_version": "v4"
    },
    {
      "timestamp": "2025-12-10T13:15:54.751003",
      "entity_type": "email",
      "entity_value": "desdruce@msn.com",
      "predicted_fraud": true,
      "actual_fraud": false,
      "risk_score": 0.55,
      "confidence": 0.7,
      "reasoning": "The entity exhibits multiple devices (6) for a single email, which is a significant risk indicator. Additionally, the standard deviation of transaction values is high, indicating a large variance in t",
      "error_type": "false_positive",
      "prompt_version": "v4"
    },
    {
      "timestamp": "2025-12-10T13:15:54.751004",
      "entity_type": "email",
      "entity_value": "NTSC___UC@outlook.com",
      "predicted_fraud": true,
      "actual_fraud": false,
      "risk_score": 0.65,
      "confidence": 0.75,
      "reasoning": "The entity shows multiple high-risk behavioral patterns, including the use of 6 unique devices and 15 unique IP addresses for a single email, which significantly elevates the risk score. Additionally,",
      "error_type": "false_positive",
      "prompt_version": "v4"
    }
  ]
}