{
  "prompt_version": "v4",
  "collected_at": "2025-12-10T13:21:47.635968",
  "entry_count": 18,
  "entries": [
    {
      "timestamp": "2025-12-10T13:21:47.635884",
      "entity_type": "email",
      "entity_value": "chrismelton522@gmail.com",
      "predicted_fraud": true,
      "actual_fraud": false,
      "risk_score": 0.65,
      "confidence": 0.75,
      "reasoning": "The entity exhibits multiple high-risk behavioral patterns, including the use of 5 unique devices and 63 unique IP addresses for a single email, which indicates suspicious behavior. Additionally, the ",
      "error_type": "false_positive",
      "prompt_version": "v4"
    },
    {
      "timestamp": "2025-12-10T13:21:47.635898",
      "entity_type": "email",
      "entity_value": "jeremy555lucas@gmail.com",
      "predicted_fraud": true,
      "actual_fraud": false,
      "risk_score": 0.65,
      "confidence": 0.75,
      "reasoning": "The entity shows suspicious behavior with a high number of unique IPs (20) while using a single device. This indicates potential account takeover or fraudulent activity. Additionally, the standard dev",
      "error_type": "false_positive",
      "prompt_version": "v4"
    },
    {
      "timestamp": "2025-12-10T13:21:47.635902",
      "entity_type": "email",
      "entity_value": "sachaa2mail@gmail.com",
      "predicted_fraud": true,
      "actual_fraud": false,
      "risk_score": 0.55,
      "confidence": 0.7,
      "reasoning": "The entity has a high number of unique IPs (20) for a relatively low number of transactions (50), which indicates suspicious behavior. Although the number of unique devices is within a normal range (3",
      "error_type": "false_positive",
      "prompt_version": "v4"
    },
    {
      "timestamp": "2025-12-10T13:21:47.635905",
      "entity_type": "email",
      "entity_value": "Kalinowskigracjan30@gmail.com",
      "predicted_fraud": true,
      "actual_fraud": false,
      "risk_score": 0.55,
      "confidence": 0.7,
      "reasoning": "The entity exhibits multiple devices (8) which is above the threshold of 3, indicating suspicious behavior. Additionally, the transaction value standard deviation is relatively high, suggesting variab",
      "error_type": "false_positive",
      "prompt_version": "v4"
    },
    {
      "timestamp": "2025-12-10T13:21:47.635908",
      "entity_type": "email",
      "entity_value": "timjurk71@gmail.com",
      "predicted_fraud": true,
      "actual_fraud": false,
      "risk_score": 0.55,
      "confidence": 0.7,
      "reasoning": "The entity shows suspicious behavior with a high number of unique IPs (52) for a single email, which indicates potential fraud risk. Although the number of unique devices is 3, the combination of high",
      "error_type": "false_positive",
      "prompt_version": "v4"
    },
    {
      "timestamp": "2025-12-10T13:21:47.635911",
      "entity_type": "email",
      "entity_value": "ida62909@gmail.com",
      "predicted_fraud": true,
      "actual_fraud": false,
      "risk_score": 0.65,
      "confidence": 0.75,
      "reasoning": "The entity shows a high risk due to the use of a single email with an unusually high number of unique IP addresses (76), which indicates suspicious behavior. The average transaction value is relativel",
      "error_type": "false_positive",
      "prompt_version": "v4"
    },
    {
      "timestamp": "2025-12-10T13:21:47.635913",
      "entity_type": "email",
      "entity_value": "nicoknoblauch@t-online.de",
      "predicted_fraud": true,
      "actual_fraud": false,
      "risk_score": 0.55,
      "confidence": 0.7,
      "reasoning": "The entity shows suspicious behavior with 11 unique IPs for only 2 devices, indicating potential account sharing or misuse. The standard deviation of transaction values is relatively high, suggesting ",
      "error_type": "false_positive",
      "prompt_version": "v4"
    },
    {
      "timestamp": "2025-12-10T13:21:47.635916",
      "entity_type": "email",
      "entity_value": "dillonj187@gmail.com",
      "predicted_fraud": true,
      "actual_fraud": false,
      "risk_score": 0.65,
      "confidence": 0.75,
      "reasoning": "The entity exhibits suspicious behavior with a high number of unique IP addresses (107) for a single email, which significantly elevates the risk score. Although the number of unique devices is within",
      "error_type": "false_positive",
      "prompt_version": "v4"
    },
    {
      "timestamp": "2025-12-10T13:21:47.635918",
      "entity_type": "email",
      "entity_value": "azmirmay003@gmail.com",
      "predicted_fraud": true,
      "actual_fraud": false,
      "risk_score": 0.55,
      "confidence": 0.7,
      "reasoning": "The entity exhibits suspicious behavior with 18 unique IPs for only 2 devices, indicating potential account takeover or fraudulent activity. The average transaction value is relatively high, and the s",
      "error_type": "false_positive",
      "prompt_version": "v4"
    },
    {
      "timestamp": "2025-12-10T13:21:47.635920",
      "entity_type": "email",
      "entity_value": "gamerlife518@yahoo.com",
      "predicted_fraud": true,
      "actual_fraud": false,
      "risk_score": 0.55,
      "confidence": 0.7,
      "reasoning": "The entity shows multiple devices (6) which is above the threshold of 3, indicating suspicious behavior. Additionally, the transaction value standard deviation is relatively high ($10.24), suggesting ",
      "error_type": "false_positive",
      "prompt_version": "v4"
    },
    {
      "timestamp": "2025-12-10T13:21:47.635923",
      "entity_type": "email",
      "entity_value": "uxhjdshhfjfjfj@gmail.com",
      "predicted_fraud": true,
      "actual_fraud": false,
      "risk_score": 0.65,
      "confidence": 0.75,
      "reasoning": "The entity shows multiple high-risk behavioral patterns, including the use of 6 unique devices and 18 unique IP addresses for a single email, which indicates suspicious behavior. Additionally, the ave",
      "error_type": "false_positive",
      "prompt_version": "v4"
    },
    {
      "timestamp": "2025-12-10T13:21:47.635925",
      "entity_type": "email",
      "entity_value": "luismariopro889@gmail.com",
      "predicted_fraud": true,
      "actual_fraud": false,
      "risk_score": 0.65,
      "confidence": 0.75,
      "reasoning": "The entity exhibits multiple devices and IPs associated with a single email, which is a strong indicator of suspicious behavior. Additionally, the transaction value variance is moderate, suggesting po",
      "error_type": "false_positive",
      "prompt_version": "v4"
    },
    {
      "timestamp": "2025-12-10T13:21:47.635927",
      "entity_type": "email",
      "entity_value": "mabtoul.sabrine@gmail.com",
      "predicted_fraud": true,
      "actual_fraud": false,
      "risk_score": 0.75,
      "confidence": 0.85,
      "reasoning": "The entity exhibits multiple high-risk behavioral patterns, including the use of 7 unique devices and 65 unique IP addresses for a single email, which significantly elevates the risk score. Additional",
      "error_type": "false_positive",
      "prompt_version": "v4"
    },
    {
      "timestamp": "2025-12-10T13:21:47.635929",
      "entity_type": "email",
      "entity_value": "bartkvaldas@gmail.com",
      "predicted_fraud": true,
      "actual_fraud": false,
      "risk_score": 0.55,
      "confidence": 0.7,
      "reasoning": "The entity exhibits multiple behavioral patterns that indicate elevated risk. While the number of unique devices (3) and unique IPs (5) is not excessively high, the average transaction value is relati",
      "error_type": "false_positive",
      "prompt_version": "v4"
    },
    {
      "timestamp": "2025-12-10T13:21:47.635932",
      "entity_type": "email",
      "entity_value": "mandachei1997@gmail.com",
      "predicted_fraud": true,
      "actual_fraud": false,
      "risk_score": 0.65,
      "confidence": 0.75,
      "reasoning": "The entity shows multiple high-risk behavioral patterns, including the use of 4 unique devices and 21 unique IP addresses for a single email, which indicates suspicious behavior. Additionally, the sta",
      "error_type": "false_positive",
      "prompt_version": "v4"
    },
    {
      "timestamp": "2025-12-10T13:21:47.635934",
      "entity_type": "email",
      "entity_value": "ridaalhge@gmail.com",
      "predicted_fraud": true,
      "actual_fraud": false,
      "risk_score": 0.55,
      "confidence": 0.7,
      "reasoning": "The entity exhibits multiple devices and IPs for a single email, which raises suspicion. Although the transaction values are relatively low and consistent, the presence of 5 unique devices and 5 uniqu",
      "error_type": "false_positive",
      "prompt_version": "v4"
    },
    {
      "timestamp": "2025-12-10T13:21:47.635936",
      "entity_type": "email",
      "entity_value": "sebastian-trouet@t-online.de",
      "predicted_fraud": true,
      "actual_fraud": false,
      "risk_score": 0.65,
      "confidence": 0.75,
      "reasoning": "The entity exhibits multiple high-risk behavioral patterns, including the use of 4 unique devices and 20 unique IP addresses for a single email, which indicates suspicious behavior. Additionally, the ",
      "error_type": "false_positive",
      "prompt_version": "v4"
    },
    {
      "timestamp": "2025-12-10T13:21:47.635938",
      "entity_type": "email",
      "entity_value": "nureetamalee@gmail.com",
      "predicted_fraud": true,
      "actual_fraud": false,
      "risk_score": 0.55,
      "confidence": 0.7,
      "reasoning": "The entity shows suspicious behavior with a high number of unique IPs (12) for a single email, which indicates potential fraud risk. Although there is only one device used, the high variance in transa",
      "error_type": "false_positive",
      "prompt_version": "v4"
    }
  ]
}